{
  "Name": "levels/mp_001/props/mp001_walkway/mp001_walkway_07",
  "PartitionGuid": "eaa8f142-cf74-11e0-8aa0-9cfe55a8c0a0",
  "PrimaryInstanceGuid": "59b38b2c-6213-7ac4-9728-bb1f88b4074f",
  "Instances": {
    "b1fd7fbd-30e2-4a8a-22f1-ebf16c3b9932": {
      "$type": "HavokAsset",
      "Scale": 1.0,
      "ExternalAssets": [],
      "Name": "Levels/MP_001/Props/MP001_walkway/MP001_walkway_07_Physics_0_Win32"
    },
    "fea8418e-2b02-5323-be6d-b4c3015dd035": {
      "$type": "HealthStateData",
      "Objects": [],
      "LoosePartPhysics": [],
      "SpawnedBangerBlueprint": null,
      "SpawnedBangerImpulseParams": null,
      "Health": 100.0,
      "PartIndex": 0,
      "PhysicsEnabled": true,
      "CopyDamageToBanger": true,
      "CanSupportOtherParts": true
    },
    "59b38b2c-6213-7ac4-9728-bb1f88b4074f": {
      "$type": "ObjectBlueprint",
      "Object": {
        "PartitionGuid": "eaa8f142-cf74-11e0-8aa0-9cfe55a8c0a0",
        "InstanceGuid": "eaa8f143-cf74-11e0-8aa0-9cfe55a8c0a0"
      },
      "EventConnections": [],
      "Descriptor": null,
      "NeedNetworkId": false,
      "InterfaceHasConnections": false,
      "AlwaysCreateEntityBusClient": false,
      "AlwaysCreateEntityBusServer": false,
      "PropertyConnections": [],
      "LinkConnections": [],
      "Name": "Levels/MP_001/Props/MP001_walkway/MP001_walkway_07"
    },
    "9e15b603-704d-daba-e72d-e72ff5e8329c": {
      "$type": "PartComponentData",
      "IsEventConnectionTarget": 3,
      "IsPropertyConnectionTarget": 3,
      "IndexInBlueprint": 1,
      "Transform": {
        "right": {
          "x": 1.0,
          "y": 0.0,
          "z": 0.0
        },
        "up": {
          "x": 0.0,
          "y": 1.0,
          "z": 0.0
        },
        "forward": {
          "x": 0.0,
          "y": 0.0,
          "z": 1.0
        },
        "trans": {
          "x": 0.0,
          "y": 0.0,
          "z": 0.0
        }
      },
      "Components": [],
      "Excluded": false,
      "HealthStates": [
        {
          "PartitionGuid": "eaa8f142-cf74-11e0-8aa0-9cfe55a8c0a0",
          "InstanceGuid": "fea8418e-2b02-5323-be6d-b4c3015dd035"
        }
      ],
      "PartLinks": [],
      "IsSupported": false,
      "IsFragile": false,
      "IsNetworkable": true,
      "IsWindow": false,
      "AnimatePhysics": false
    },
    "861da382-2b3d-d375-59ff-8f66dcb8f95c": {
      "$type": "PhysicsEntityData",
      "IsEventConnectionTarget": 3,
      "IsPropertyConnectionTarget": 3,
      "IndexInBlueprint": 65535,
      "Asset": null,
      "ScaledAssets": [
        {
          "PartitionGuid": "eaa8f142-cf74-11e0-8aa0-9cfe55a8c0a0",
          "InstanceGuid": "b1fd7fbd-30e2-4a8a-22f1-ebf16c3b9932"
        }
      ],
      "RigidBodies": [
        {
          "PartitionGuid": "eaa8f142-cf74-11e0-8aa0-9cfe55a8c0a0",
          "InstanceGuid": "b554dcc4-3140-2d60-af40-5cd0d6f7d937"
        }
      ],
      "EncapsulatePartsInLists": false,
      "FloatPhysics": null,
      "Mass": 1000010.0,
      "InertiaModifier": {
        "x": 1.0,
        "y": 1.0,
        "z": 1.0
      },
      "Friction": 1000010.0,
      "Restitution": 1000010.0,
      "AngularVelocityDamping": -1.0,
      "LinearVelocityDamping": -1.0,
      "Proximity": null,
      "Constraints": [],
      "MovableParts": false
    },
    "b554dcc4-3140-2d60-af40-5cd0d6f7d937": {
      "$type": "RigidBodyData",
      "RigidBodyType": 0,
      "Mass": 0.0,
      "Friction": 0.5,
      "Restitution": 0.4,
      "InertiaModifier": {
        "x": 1.0,
        "y": 1.0,
        "z": 1.0
      },
      "AngularVelocityDamping": -1.0,
      "LinearVelocityDamping": -1.0,
      "InteractionToolkitCollisionVolumeId": 0,
      "MotionType": 1,
      "QualityType": 0,
      "CollisionLayer": 0,
      "FloatPhysics": null,
      "Constraints": []
    },
    "eaa8f143-cf74-11e0-8aa0-9cfe55a8c0a0": {
      "$type": "StaticModelEntityData",
      "IsEventConnectionTarget": 2,
      "IsPropertyConnectionTarget": 2,
      "IndexInBlueprint": 0,
      "Transform": {
        "right": {
          "x": 1.0,
          "y": 0.0,
          "z": 0.0
        },
        "up": {
          "x": 0.0,
          "y": 1.0,
          "z": 0.0
        },
        "forward": {
          "x": 0.0,
          "y": 0.0,
          "z": 1.0
        },
        "trans": {
          "x": 0.0,
          "y": 0.0,
          "z": 0.0
        }
      },
      "Enabled": true,
      "Components": [
        {
          "PartitionGuid": "eaa8f142-cf74-11e0-8aa0-9cfe55a8c0a0",
          "InstanceGuid": "9e15b603-704d-daba-e72d-e72ff5e8329c"
        }
      ],
      "RuntimeComponentCount": 1,
      "PhysicsData": {
        "PartitionGuid": "eaa8f142-cf74-11e0-8aa0-9cfe55a8c0a0",
        "InstanceGuid": "861da382-2b3d-d375-59ff-8f66dcb8f95c"
      },
      "PartLinks": [],
      "Mesh": {
        "PartitionGuid": "036a1ed2-c319-6e0f-c47c-126a9f73350d",
        "InstanceGuid": "d9f9ec7a-d930-c4ce-918f-114343db556d"
      },
      "BoneCount": 0,
      "BasePoseTransforms": [],
      "NetworkInfo": {
        "PartNetworkIdRanges": [
          {
            "First": 4294967295,
            "Last": 4294967295
          }
        ],
        "NetworkIdCount": 0,
        "ChildNetworkInfos": [],
        "ChildNetworkIdCount": 0
      },
      "PhysicsPartInfos": [
        {
          "PartComponentIndex": 0,
          "HealthStateIndex": 0
        }
      ],
      "ExcludeFromNearbyObjectDestruction": false,
      "AnimatePhysics": false,
      "Visible": true
    }
  }
}