{
  "Name": "xp_raw/architecture/gasstation_01/gasstation_01",
  "PartitionGuid": "aa54270d-74a9-11e0-9162-ffe445878a5b",
  "PrimaryInstanceGuid": "c35170d9-3bdc-a866-9f50-52845beec43a",
  "Instances": {
    "08b2a393-7b2d-e942-c054-3ffe7b69b0b3": {
      "$type": "HealthStateData",
      "Objects": [],
      "LoosePartPhysics": [],
      "SpawnedBangerBlueprint": null,
      "SpawnedBangerImpulseParams": null,
      "Health": 100.0,
      "PartIndex": 0,
      "PhysicsEnabled": true,
      "CopyDamageToBanger": true,
      "CanSupportOtherParts": true
    },
    "0f18c217-2f9d-aaa9-4eb1-c115aa308c56": {
      "$type": "PartComponentData",
      "IndexInBlueprint": 1,
      "IsEventConnectionTarget": 3,
      "IsPropertyConnectionTarget": 3,
      "Transform": {
        "right": {
          "x": 1.0,
          "y": 0.0,
          "z": 0.0
        },
        "up": {
          "x": 0.0,
          "y": 1.0,
          "z": 0.0
        },
        "forward": {
          "x": 0.0,
          "y": 0.0,
          "z": 1.0
        },
        "trans": {
          "x": 0.0,
          "y": 0.0,
          "z": 0.0
        }
      },
      "Components": [],
      "Excluded": false,
      "HealthStates": [
        {
          "PartitionGuid": "aa54270d-74a9-11e0-9162-ffe445878a5b",
          "InstanceGuid": "08b2a393-7b2d-e942-c054-3ffe7b69b0b3"
        }
      ],
      "PartLinks": [],
      "IsSupported": false,
      "IsFragile": false,
      "IsNetworkable": true,
      "IsWindow": false,
      "AnimatePhysics": false
    },
    "2e106ed6-ee26-52b2-d5ad-50a71ef3a188": {
      "$type": "HavokAsset",
      "Name": "XP_Raw/Architecture/GasStation_01/GasStation_01_Physics_0_Win32",
      "Scale": 1.0,
      "ExternalAssets": []
    },
    "4ead18fc-fbdb-4f8d-5199-c27fc763a0ab": {
      "$type": "RigidBodyData",
      "InertiaModifier": {
        "x": 1.0,
        "y": 1.0,
        "z": 1.0
      },
      "RigidBodyType": 0,
      "Mass": 0.0,
      "Restitution": 0.4,
      "Friction": 0.5,
      "AngularVelocityDamping": -1.0,
      "LinearVelocityDamping": -1.0,
      "InteractionToolkitCollisionVolumeId": 0,
      "MotionType": 1,
      "QualityType": 0,
      "CollisionLayer": 0,
      "FloatPhysics": null,
      "Constraints": []
    },
    "a697d4f1-dab0-7041-51eb-6f2f67101212": {
      "$type": "PhysicsEntityData",
      "IndexInBlueprint": 65535,
      "IsEventConnectionTarget": 3,
      "IsPropertyConnectionTarget": 3,
      "InertiaModifier": {
        "x": 1.0,
        "y": 1.0,
        "z": 1.0
      },
      "ScaledAssets": [
        {
          "PartitionGuid": "aa54270d-74a9-11e0-9162-ffe445878a5b",
          "InstanceGuid": "2e106ed6-ee26-52b2-d5ad-50a71ef3a188"
        }
      ],
      "RigidBodies": [
        {
          "PartitionGuid": "aa54270d-74a9-11e0-9162-ffe445878a5b",
          "InstanceGuid": "4ead18fc-fbdb-4f8d-5199-c27fc763a0ab"
        }
      ],
      "Asset": null,
      "FloatPhysics": null,
      "Mass": 1000010.0,
      "Restitution": 1000010.0,
      "Friction": 1000010.0,
      "LinearVelocityDamping": -1.0,
      "AngularVelocityDamping": -1.0,
      "Proximity": null,
      "Constraints": [],
      "EncapsulatePartsInLists": false,
      "MovableParts": false
    },
    "aa54270e-74a9-11e0-9162-ffe445878a5b": {
      "$type": "StaticModelEntityData",
      "IndexInBlueprint": 0,
      "IsEventConnectionTarget": 2,
      "IsPropertyConnectionTarget": 2,
      "Transform": {
        "right": {
          "x": 1.0,
          "y": 0.0,
          "z": 0.0
        },
        "up": {
          "x": 0.0,
          "y": 1.0,
          "z": 0.0
        },
        "forward": {
          "x": 0.0,
          "y": 0.0,
          "z": 1.0
        },
        "trans": {
          "x": 0.0,
          "y": 0.0,
          "z": 0.0
        }
      },
      "Components": [
        {
          "PartitionGuid": "aa54270d-74a9-11e0-9162-ffe445878a5b",
          "InstanceGuid": "0f18c217-2f9d-aaa9-4eb1-c115aa308c56"
        }
      ],
      "Enabled": true,
      "RuntimeComponentCount": 1,
      "PhysicsData": {
        "PartitionGuid": "aa54270d-74a9-11e0-9162-ffe445878a5b",
        "InstanceGuid": "a697d4f1-dab0-7041-51eb-6f2f67101212"
      },
      "PartLinks": [],
      "Mesh": {
        "PartitionGuid": "4f40da74-a093-dc22-6eea-2288d7e47066",
        "InstanceGuid": "59b4a87b-95d3-4a81-e8d8-4ee8d129efa1"
      },
      "BoneCount": 0,
      "BasePoseTransforms": [],
      "NetworkInfo": {
        "PartNetworkIdRanges": [
          {
            "First": 4294967295,
            "Last": 4294967295
          }
        ],
        "NetworkIdCount": 0,
        "ChildNetworkInfos": [],
        "ChildNetworkIdCount": 0
      },
      "PhysicsPartInfos": [
        {
          "PartComponentIndex": 0,
          "HealthStateIndex": 0
        }
      ],
      "ExcludeFromNearbyObjectDestruction": false,
      "AnimatePhysics": false,
      "Visible": true
    },
    "c35170d9-3bdc-a866-9f50-52845beec43a": {
      "$type": "ObjectBlueprint",
      "Name": "XP_Raw/Architecture/GasStation_01/GasStation_01",
      "PropertyConnections": [],
      "LinkConnections": [],
      "EventConnections": [],
      "Descriptor": null,
      "NeedNetworkId": false,
      "InterfaceHasConnections": false,
      "AlwaysCreateEntityBusClient": false,
      "AlwaysCreateEntityBusServer": false,
      "Object": {
        "PartitionGuid": "aa54270d-74a9-11e0-9162-ffe445878a5b",
        "InstanceGuid": "aa54270e-74a9-11e0-9162-ffe445878a5b"
      }
    }
  }
}