{
  "Name": "sound/vo/en/sp/sp09/sp09_02_sc36_03_cole",
  "PartitionGuid": "eb0e053e-bea4-11e0-804b-827d7ac7a2ac",
  "PrimaryInstanceGuid": "f14ea109-f923-d2c0-f9d9-a804bfe85b5a",
  "Instances": {
    "f14ea109-f923-d2c0-f9d9-a804bfe85b5a": {
      "$type": "SoundWaveAsset",
      "Variations": [
        {
          "PartitionGuid": "eb0e053e-bea4-11e0-804b-827d7ac7a2ac",
          "InstanceGuid": "ea53105f-961e-cb3b-875f-aebea071a153"
        },
        {
          "PartitionGuid": "eb0e053e-bea4-11e0-804b-827d7ac7a2ac",
          "InstanceGuid": "16f8dbec-371c-54c6-f1c0-79d9910b4e46"
        },
        {
          "PartitionGuid": "eb0e053e-bea4-11e0-804b-827d7ac7a2ac",
          "InstanceGuid": "010c11b2-7b13-6124-58d8-5e6e04ae9877"
        },
        {
          "PartitionGuid": "eb0e053e-bea4-11e0-804b-827d7ac7a2ac",
          "InstanceGuid": "23463fdd-4ee9-467f-3b4c-1d378c439723"
        },
        {
          "PartitionGuid": "eb0e053e-bea4-11e0-804b-827d7ac7a2ac",
          "InstanceGuid": "6dce590f-5e0f-52d2-9c75-d7022863bca5"
        },
        {
          "PartitionGuid": "eb0e053e-bea4-11e0-804b-827d7ac7a2ac",
          "InstanceGuid": "5f5f124c-9a8c-20b7-2a41-755745e8710a"
        },
        {
          "PartitionGuid": "eb0e053e-bea4-11e0-804b-827d7ac7a2ac",
          "InstanceGuid": "80472232-2c36-b864-4e6e-300825deacee"
        },
        {
          "PartitionGuid": "eb0e053e-bea4-11e0-804b-827d7ac7a2ac",
          "InstanceGuid": "594a6492-43fd-a0fb-4942-7d06b37bf494"
        }
      ],
      "Localization": [
        {
          "Language": {
            "PartitionGuid": "0ddf7c04-9ea3-11dd-8413-9752fc5e9f27",
            "InstanceGuid": "6ea78aff-8e78-4dd3-9907-ae523f5593cb"
          },
          "FirstVariationIndex": 0,
          "VariationCount": 1
        },
        {
          "Language": {
            "PartitionGuid": "0ddf7c04-9ea3-11dd-8413-9752fc5e9f27",
            "InstanceGuid": "9790295d-f622-4b87-a119-d13c6595c313"
          },
          "FirstVariationIndex": 1,
          "VariationCount": 1
        },
        {
          "Language": {
            "PartitionGuid": "0ddf7c04-9ea3-11dd-8413-9752fc5e9f27",
            "InstanceGuid": "d3d096ca-2afa-43e4-9136-bb54d9440b3d"
          },
          "FirstVariationIndex": 6,
          "VariationCount": 1
        },
        {
          "Language": {
            "PartitionGuid": "0ddf7c04-9ea3-11dd-8413-9752fc5e9f27",
            "InstanceGuid": "68fa3a18-eec0-4c91-8cb6-6100f3ed16ec"
          },
          "FirstVariationIndex": 5,
          "VariationCount": 1
        },
        {
          "Language": {
            "PartitionGuid": "0ddf7c04-9ea3-11dd-8413-9752fc5e9f27",
            "InstanceGuid": "05523de9-26c2-4602-903b-4495f043e951"
          },
          "FirstVariationIndex": 4,
          "VariationCount": 1
        },
        {
          "Language": {
            "PartitionGuid": "0ddf7c04-9ea3-11dd-8413-9752fc5e9f27",
            "InstanceGuid": "bf67a8d0-ec6a-417e-b659-2ea9b5eec98e"
          },
          "FirstVariationIndex": 3,
          "VariationCount": 1
        },
        {
          "Language": {
            "PartitionGuid": "0ddf7c04-9ea3-11dd-8413-9752fc5e9f27",
            "InstanceGuid": "f74a913b-7669-4256-bc60-f6d668b78ce6"
          },
          "FirstVariationIndex": 7,
          "VariationCount": 1
        },
        {
          "Language": {
            "PartitionGuid": "0ddf7c04-9ea3-11dd-8413-9752fc5e9f27",
            "InstanceGuid": "c5e6fc15-3418-4fcc-9eb6-84a1fe3e509c"
          },
          "FirstVariationIndex": 2,
          "VariationCount": 1
        }
      ],
      "SubtitleStringIds": [],
      "Selection": 1,
      "StreamPool": {
        "PartitionGuid": "b041d7b6-b205-4024-87bf-07794b5c5657",
        "InstanceGuid": "aae1b0f4-029d-4c77-88dc-c03a1e5b82de"
      },
      "Seekable": false,
      "PreferAvailableVariations": true,
      "PersistentVariationCount": 0,
      "ChannelCount": 1,
      "VoicePriority": 4,
      "PrimePriority": 0,
      "RequestPriority": 0,
      "NameHash": 4266581545,
      "Chunks": [
        {
          "ChunkId": "0732fb97-c191-8a81-4cf1-b5a2605d9a9a",
          "ChunkSize": 14444
        },
        {
          "ChunkId": "155a93e7-4b8c-8d0c-7ed1-00ff0d57689c",
          "ChunkSize": 14444
        },
        {
          "ChunkId": "59445905-922b-7a06-1bc1-36b73848ab5a",
          "ChunkSize": 14444
        },
        {
          "ChunkId": "62e69d19-b416-5eec-f71f-37ba5644f54c",
          "ChunkSize": 14444
        },
        {
          "ChunkId": "05fb1901-101a-8a40-7b5b-a64adba48578",
          "ChunkSize": 14444
        },
        {
          "ChunkId": "75b1925a-8161-02b1-92e2-18d3d6e61ec8",
          "ChunkSize": 14444
        },
        {
          "ChunkId": "59484341-2223-6782-5cfe-a544269c5bfe",
          "ChunkSize": 14444
        },
        {
          "ChunkId": "2c4d64d6-7556-6c6a-0c24-4da445f719e0",
          "ChunkSize": 14444
        }
      ],
      "Name": "Sound/VO/EN/SP/sp09/sp09_02_sc36_03_Cole"
    },
    "ea53105f-961e-cb3b-875f-aebea071a153": {
      "$type": "SoundWaveVariation",
      "Subtitles": [],
      "SeekTablesSize": 0,
      "Segments": [
        {
          "SamplesOffset": 0,
          "SeekTableOffset": 4294967295,
          "SegmentLength": 1.51
        }
      ],
      "ChunkIndex": 0,
      "FirstLoopSegmentIndex": 0,
      "LastLoopSegmentIndex": 0
    },
    "16f8dbec-371c-54c6-f1c0-79d9910b4e46": {
      "$type": "SoundWaveVariation",
      "Subtitles": [],
      "SeekTablesSize": 0,
      "Segments": [
        {
          "SamplesOffset": 0,
          "SeekTableOffset": 4294967295,
          "SegmentLength": 1.51
        }
      ],
      "ChunkIndex": 1,
      "FirstLoopSegmentIndex": 0,
      "LastLoopSegmentIndex": 0
    },
    "010c11b2-7b13-6124-58d8-5e6e04ae9877": {
      "$type": "SoundWaveVariation",
      "Subtitles": [],
      "SeekTablesSize": 0,
      "Segments": [
        {
          "SamplesOffset": 0,
          "SeekTableOffset": 4294967295,
          "SegmentLength": 1.51
        }
      ],
      "ChunkIndex": 7,
      "FirstLoopSegmentIndex": 0,
      "LastLoopSegmentIndex": 0
    },
    "23463fdd-4ee9-467f-3b4c-1d378c439723": {
      "$type": "SoundWaveVariation",
      "Subtitles": [],
      "SeekTablesSize": 0,
      "Segments": [
        {
          "SamplesOffset": 0,
          "SeekTableOffset": 4294967295,
          "SegmentLength": 1.51
        }
      ],
      "ChunkIndex": 5,
      "FirstLoopSegmentIndex": 0,
      "LastLoopSegmentIndex": 0
    },
    "6dce590f-5e0f-52d2-9c75-d7022863bca5": {
      "$type": "SoundWaveVariation",
      "Subtitles": [],
      "SeekTablesSize": 0,
      "Segments": [
        {
          "SamplesOffset": 0,
          "SeekTableOffset": 4294967295,
          "SegmentLength": 1.51
        }
      ],
      "ChunkIndex": 4,
      "FirstLoopSegmentIndex": 0,
      "LastLoopSegmentIndex": 0
    },
    "5f5f124c-9a8c-20b7-2a41-755745e8710a": {
      "$type": "SoundWaveVariation",
      "Subtitles": [],
      "SeekTablesSize": 0,
      "Segments": [
        {
          "SamplesOffset": 0,
          "SeekTableOffset": 4294967295,
          "SegmentLength": 1.51
        }
      ],
      "ChunkIndex": 3,
      "FirstLoopSegmentIndex": 0,
      "LastLoopSegmentIndex": 0
    },
    "80472232-2c36-b864-4e6e-300825deacee": {
      "$type": "SoundWaveVariation",
      "Subtitles": [],
      "SeekTablesSize": 0,
      "Segments": [
        {
          "SamplesOffset": 0,
          "SeekTableOffset": 4294967295,
          "SegmentLength": 1.51
        }
      ],
      "ChunkIndex": 2,
      "FirstLoopSegmentIndex": 0,
      "LastLoopSegmentIndex": 0
    },
    "594a6492-43fd-a0fb-4942-7d06b37bf494": {
      "$type": "SoundWaveVariation",
      "Subtitles": [],
      "SeekTablesSize": 0,
      "Segments": [
        {
          "SamplesOffset": 0,
          "SeekTableOffset": 4294967295,
          "SegmentLength": 1.51
        }
      ],
      "ChunkIndex": 6,
      "FirstLoopSegmentIndex": 0,
      "LastLoopSegmentIndex": 0
    }
  }
}