{
  "Name": "levels/sp_bank/house_props_sub/layer0_house_props",
  "PartitionGuid": "1dcef3b9-66e1-475f-a10c-92e4c80772a0",
  "PrimaryInstanceGuid": "5d7f14ad-fdff-4f19-a22d-5135f8da4dc1",
  "Instances": {
    "409250d6-6126-49f2-a352-2b704aecf5bb": {
      "$type": "ReferenceObjectData",
      "IndexInBlueprint": 6,
      "IsEventConnectionTarget": 3,
      "IsPropertyConnectionTarget": 3,
      "BlueprintTransform": {
        "right": {
          "x": 0.9510564,
          "y": 1.0560521E-15,
          "z": -0.3090172
        },
        "up": {
          "x": -0.3090172,
          "y": -4.371139E-08,
          "z": -0.9510565
        },
        "forward": {
          "x": -1.4150917E-08,
          "y": 1.0,
          "z": -4.211873E-08
        },
        "trans": {
          "x": -984.6177,
          "y": 159.30598,
          "z": -321.3423
        }
      },
      "Blueprint": {
        "PartitionGuid": "07a821e3-fa0a-11de-9399-b0f9de326a59",
        "InstanceGuid": "9da25321-308c-ef36-0e3d-5d853232163a"
      },
      "ObjectVariation": null,
      "StreamRealm": "StreamRealm_None",
      "CastSunShadowEnable": true,
      "Excluded": false
    },
    "5d7f14ad-fdff-4f19-a22d-5135f8da4dc1": {
      "$type": "WorldPartData",
      "Name": "Levels/SP_Bank/House_Props",
      "PropertyConnections": [],
      "LinkConnections": [],
      "EventConnections": [],
      "Descriptor": null,
      "NeedNetworkId": false,
      "InterfaceHasConnections": false,
      "AlwaysCreateEntityBusClient": false,
      "AlwaysCreateEntityBusServer": false,
      "Objects": [
        {
          "PartitionGuid": "1dcef3b9-66e1-475f-a10c-92e4c80772a0",
          "InstanceGuid": "b91848a6-4e71-430b-a784-23cbe8f33606"
        },
        {
          "PartitionGuid": "1dcef3b9-66e1-475f-a10c-92e4c80772a0",
          "InstanceGuid": "b2d6c745-529a-4ddc-8ed3-ea69ac7ac0ce"
        },
        {
          "PartitionGuid": "1dcef3b9-66e1-475f-a10c-92e4c80772a0",
          "InstanceGuid": "6fed596d-7b21-4c39-84c8-d3a4a8e4b1e2"
        },
        {
          "PartitionGuid": "1dcef3b9-66e1-475f-a10c-92e4c80772a0",
          "InstanceGuid": "f50292c7-22f2-4c0e-9b92-d062cfcf95d9"
        },
        {
          "PartitionGuid": "1dcef3b9-66e1-475f-a10c-92e4c80772a0",
          "InstanceGuid": "409250d6-6126-49f2-a352-2b704aecf5bb"
        },
        {
          "PartitionGuid": "1dcef3b9-66e1-475f-a10c-92e4c80772a0",
          "InstanceGuid": "b3945917-9f08-4857-b6aa-ae17118ac70e"
        },
        {
          "PartitionGuid": "1dcef3b9-66e1-475f-a10c-92e4c80772a0",
          "InstanceGuid": "69609a30-7db5-49e2-b861-3050e68e5550"
        },
        {
          "PartitionGuid": "1dcef3b9-66e1-475f-a10c-92e4c80772a0",
          "InstanceGuid": "d9de2bac-ff16-9390-6f7d-e77b4114ca27"
        },
        {
          "PartitionGuid": "1dcef3b9-66e1-475f-a10c-92e4c80772a0",
          "InstanceGuid": "fb5c80b7-fb82-b67f-0d0c-e02764c64de5"
        },
        {
          "PartitionGuid": "1dcef3b9-66e1-475f-a10c-92e4c80772a0",
          "InstanceGuid": "b7fe37c0-7fb5-d1b3-7aa3-d05eff8b540f"
        }
      ],
      "HackToSolveRealTimeTweakingIssue": "cafbc71a-a124-938e-7fae-6aaae3521013",
      "UseDeferredEntityCreation": false,
      "Enabled": true
    },
    "69609a30-7db5-49e2-b861-3050e68e5550": {
      "$type": "ReferenceObjectData",
      "IndexInBlueprint": 8,
      "IsEventConnectionTarget": 3,
      "IsPropertyConnectionTarget": 3,
      "BlueprintTransform": {
        "right": {
          "x": 0.9510564,
          "y": 1.7802786E-15,
          "z": -0.3090172
        },
        "up": {
          "x": -0.3090172,
          "y": -4.371139E-08,
          "z": -0.9510565
        },
        "forward": {
          "x": -1.4150917E-08,
          "y": 1.0,
          "z": -4.211873E-08
        },
        "trans": {
          "x": -986.9907,
          "y": 159.30598,
          "z": -328.64655
        }
      },
      "Blueprint": {
        "PartitionGuid": "07a821e3-fa0a-11de-9399-b0f9de326a59",
        "InstanceGuid": "9da25321-308c-ef36-0e3d-5d853232163a"
      },
      "ObjectVariation": null,
      "StreamRealm": "StreamRealm_None",
      "CastSunShadowEnable": true,
      "Excluded": false
    },
    "6fed596d-7b21-4c39-84c8-d3a4a8e4b1e2": {
      "$type": "ReferenceObjectData",
      "IndexInBlueprint": 4,
      "IsEventConnectionTarget": 3,
      "IsPropertyConnectionTarget": 3,
      "BlueprintTransform": {
        "right": {
          "x": 0.9510564,
          "y": 1.7802786E-15,
          "z": -0.3090172
        },
        "up": {
          "x": -0.3090172,
          "y": -4.371139E-08,
          "z": -0.9510565
        },
        "forward": {
          "x": -1.4150917E-08,
          "y": 1.0,
          "z": -4.211873E-08
        },
        "trans": {
          "x": -988.17725,
          "y": 159.30598,
          "z": -332.29868
        }
      },
      "Blueprint": {
        "PartitionGuid": "07a821e3-fa0a-11de-9399-b0f9de326a59",
        "InstanceGuid": "9da25321-308c-ef36-0e3d-5d853232163a"
      },
      "ObjectVariation": null,
      "StreamRealm": "StreamRealm_None",
      "CastSunShadowEnable": true,
      "Excluded": false
    },
    "b2d6c745-529a-4ddc-8ed3-ea69ac7ac0ce": {
      "$type": "ReferenceObjectData",
      "IndexInBlueprint": 3,
      "IsEventConnectionTarget": 3,
      "IsPropertyConnectionTarget": 3,
      "BlueprintTransform": {
        "right": {
          "x": 0.30429342,
          "y": 0.0,
          "z": 0.95257837
        },
        "up": {
          "x": 0.0,
          "y": 1.0,
          "z": 0.0
        },
        "forward": {
          "x": -0.95257837,
          "y": 0.0,
          "z": 0.30429342
        },
        "trans": {
          "x": -989.6392,
          "y": 155.88649,
          "z": -343.39804
        }
      },
      "Blueprint": {
        "PartitionGuid": "9fe57f50-0814-11e0-8e28-8ee4f2746e6b",
        "InstanceGuid": "ea1fc56e-ccb8-3e9b-bd0c-8ab5f9b22dfd"
      },
      "ObjectVariation": null,
      "StreamRealm": "StreamRealm_None",
      "CastSunShadowEnable": true,
      "Excluded": false
    },
    "b3945917-9f08-4857-b6aa-ae17118ac70e": {
      "$type": "ReferenceObjectData",
      "IndexInBlueprint": 7,
      "IsEventConnectionTarget": 3,
      "IsPropertyConnectionTarget": 3,
      "BlueprintTransform": {
        "right": {
          "x": 0.9510564,
          "y": 1.7802786E-15,
          "z": -0.3090172
        },
        "up": {
          "x": -0.3090172,
          "y": -4.371139E-08,
          "z": -0.9510565
        },
        "forward": {
          "x": -1.4150917E-08,
          "y": 1.0,
          "z": -4.211873E-08
        },
        "trans": {
          "x": -985.8042,
          "y": 159.30598,
          "z": -324.99442
        }
      },
      "Blueprint": {
        "PartitionGuid": "07a821e3-fa0a-11de-9399-b0f9de326a59",
        "InstanceGuid": "9da25321-308c-ef36-0e3d-5d853232163a"
      },
      "ObjectVariation": null,
      "StreamRealm": "StreamRealm_None",
      "CastSunShadowEnable": true,
      "Excluded": false
    },
    "b7fe37c0-7fb5-d1b3-7aa3-d05eff8b540f": {
      "$type": "ReferenceObjectData",
      "IndexInBlueprint": 11,
      "IsEventConnectionTarget": 3,
      "IsPropertyConnectionTarget": 3,
      "BlueprintTransform": {
        "right": {
          "x": 1.0,
          "y": 0.0,
          "z": 0.0
        },
        "up": {
          "x": 0.0,
          "y": 1.0,
          "z": 0.0
        },
        "forward": {
          "x": 0.0,
          "y": 0.0,
          "z": 1.0
        },
        "trans": {
          "x": -989.2126,
          "y": 159.41167,
          "z": -339.78232
        }
      },
      "Blueprint": {
        "PartitionGuid": "2504bbf9-7344-ac78-a187-dd14054ab6f4",
        "InstanceGuid": "2504bbf9-7344-ac78-a187-dd14054ab6f4"
      },
      "ObjectVariation": null,
      "StreamRealm": "StreamRealm_None",
      "CastSunShadowEnable": true,
      "Excluded": false
    },
    "b91848a6-4e71-430b-a784-23cbe8f33606": {
      "$type": "ReferenceObjectData",
      "IndexInBlueprint": 2,
      "IsEventConnectionTarget": 3,
      "IsPropertyConnectionTarget": 3,
      "BlueprintTransform": {
        "right": {
          "x": 0.009061666,
          "y": 0.0,
          "z": 0.999959
        },
        "up": {
          "x": 0.0,
          "y": 1.0,
          "z": 0.0
        },
        "forward": {
          "x": -0.999959,
          "y": 0.0,
          "z": 0.009061666
        },
        "trans": {
          "x": -995.66864,
          "y": 155.88388,
          "z": -341.1214
        }
      },
      "Blueprint": {
        "PartitionGuid": "42c87cb9-fe3f-11df-a17b-a14bda548ef0",
        "InstanceGuid": "4b9f60b2-1931-cb2c-fcb2-97589bf5dde8"
      },
      "ObjectVariation": null,
      "StreamRealm": "StreamRealm_None",
      "CastSunShadowEnable": true,
      "Excluded": false
    },
    "d9de2bac-ff16-9390-6f7d-e77b4114ca27": {
      "$type": "ReferenceObjectData",
      "IndexInBlueprint": 9,
      "IsEventConnectionTarget": 3,
      "IsPropertyConnectionTarget": 3,
      "BlueprintTransform": {
        "right": {
          "x": 1.0,
          "y": 0.0,
          "z": 0.0
        },
        "up": {
          "x": 0.0,
          "y": 1.0,
          "z": 0.0
        },
        "forward": {
          "x": 0.0,
          "y": 0.0,
          "z": 1.0
        },
        "trans": {
          "x": -987.2953,
          "y": 159.41167,
          "z": -333.48923
        }
      },
      "Blueprint": {
        "PartitionGuid": "2504bbf9-7344-ac78-a187-dd14054ab6f4",
        "InstanceGuid": "2504bbf9-7344-ac78-a187-dd14054ab6f4"
      },
      "ObjectVariation": null,
      "StreamRealm": "StreamRealm_None",
      "CastSunShadowEnable": true,
      "Excluded": false
    },
    "f50292c7-22f2-4c0e-9b92-d062cfcf95d9": {
      "$type": "ReferenceObjectData",
      "IndexInBlueprint": 5,
      "IsEventConnectionTarget": 3,
      "IsPropertyConnectionTarget": 3,
      "BlueprintTransform": {
        "right": {
          "x": 0.9510564,
          "y": 1.7802786E-15,
          "z": -0.3090172
        },
        "up": {
          "x": -0.3090172,
          "y": -4.371139E-08,
          "z": -0.9510565
        },
        "forward": {
          "x": -1.4150917E-08,
          "y": 1.0,
          "z": -4.211873E-08
        },
        "trans": {
          "x": -989.3638,
          "y": 159.30598,
          "z": -335.9508
        }
      },
      "Blueprint": {
        "PartitionGuid": "07a821e3-fa0a-11de-9399-b0f9de326a59",
        "InstanceGuid": "9da25321-308c-ef36-0e3d-5d853232163a"
      },
      "ObjectVariation": null,
      "StreamRealm": "StreamRealm_None",
      "CastSunShadowEnable": true,
      "Excluded": false
    },
    "fb5c80b7-fb82-b67f-0d0c-e02764c64de5": {
      "$type": "ReferenceObjectData",
      "IndexInBlueprint": 10,
      "IsEventConnectionTarget": 3,
      "IsPropertyConnectionTarget": 3,
      "BlueprintTransform": {
        "right": {
          "x": 1.0,
          "y": 0.0,
          "z": 0.0
        },
        "up": {
          "x": 0.0,
          "y": 1.0,
          "z": 0.0
        },
        "forward": {
          "x": 0.0,
          "y": 0.0,
          "z": 1.0
        },
        "trans": {
          "x": -985.1285,
          "y": 159.41167,
          "z": -326.9004
        }
      },
      "Blueprint": {
        "PartitionGuid": "2504bbf9-7344-ac78-a187-dd14054ab6f4",
        "InstanceGuid": "2504bbf9-7344-ac78-a187-dd14054ab6f4"
      },
      "ObjectVariation": null,
      "StreamRealm": "StreamRealm_None",
      "CastSunShadowEnable": true,
      "Excluded": false
    }
  }
}